pyfuncschedule/__init__.py
pyfuncschedule/async_iter.py
pyfuncschedule/grammar.py
pyfuncschedule/parser.py
pyfuncschedule-0.1.dist-info/LICENSE
pyfuncschedule-0.1.dist-info/METADATA
pyfuncschedule-0.1.dist-info/WHEEL
pyfuncschedule-0.1.dist-info/top_level.txt
pyfuncschedule-0.1.dist-info/RECORD
