Metadata-Version: 2.1
Name: pyfuncschedule
Version: 0.1
Summary: A simple schedule parser/runner with a convienient syntax.
Home-page: https://github.com/BenedictWilkins/pyfuncschedule
Author: Benedict Wilkins
Author-email: benrjw@gmail.com
Classifier: Development Status :: 5 - Production/Stable
Classifier: Intended Audience :: Developers
Classifier: License :: OSI Approved :: GNU General Public License v3 (GPLv3)
Classifier: Programming Language :: Python :: 3.10
Requires-Python: >=3.10
License-File: LICENSE
Requires-Dist: pyparsing
Requires-Dist: aiostream
